reviewbotext/__init__.py
reviewbotext/admin.py
reviewbotext/admin_urls.py
reviewbotext/extension.py
reviewbotext/forms.py
reviewbotext/integration.py
reviewbotext/models.py
reviewbotext/resources.py
reviewbotext/views.py
reviewbotext/widgets.py
reviewbotext/evolutions/__init__.py
reviewbotext/evolutions/old_tool_model.py
reviewbotext/evolutions/tool_working_directory_required.py
reviewbotext/static/staticfiles.json
reviewbotext/static/css/extension-config.css
reviewbotext/static/css/extension-config.css.map
reviewbotext/static/css/extension-config.e957332d6332.less
reviewbotext/static/css/extension-config.less
reviewbotext/static/css/extension-config.min.2004e5f0b671.css
reviewbotext/static/css/extension-config.min.b9ef5b8e37d5.css
reviewbotext/static/css/extension-config.min.css
reviewbotext/static/css/integration-config.b019a5482c9f.less
reviewbotext/static/css/integration-config.css
reviewbotext/static/css/integration-config.css.map
reviewbotext/static/css/integration-config.less
reviewbotext/static/css/integration-config.min.31e030df2d08.css
reviewbotext/static/css/integration-config.min.555b52530726.css
reviewbotext/static/css/integration-config.min.css
reviewbotext/static/images/reviewbot.fa2d2b96e4ce.png
reviewbotext/static/images/reviewbot.png
reviewbotext/static/images/reviewbot@2x.90e39b799a6e.png
reviewbotext/static/images/reviewbot@2x.png
reviewbotext/static/js/extension-config.min.95b513f0e569.js
reviewbotext/static/js/extension-config.min.js
reviewbotext/static/js/extensionConfig.es6.425b0fe188db.js
reviewbotext/static/js/extensionConfig.es6.js
reviewbotext/static/js/extensionConfig.js
reviewbotext/static/js/extensionConfig.js.map
reviewbotext/static/js/integration-config.min.8682044934af.js
reviewbotext/static/js/integration-config.min.js
reviewbotext/static/js/integrationConfig.es6.b0ac3d250a18.js
reviewbotext/static/js/integrationConfig.es6.js
reviewbotext/static/js/integrationConfig.js
reviewbotext/static/js/integrationConfig.js.map
reviewbot_extension-4.0.dist-info/METADATA
reviewbot_extension-4.0.dist-info/WHEEL
reviewbot_extension-4.0.dist-info/entry_points.txt
reviewbot_extension-4.0.dist-info/top_level.txt
reviewbot_extension-4.0.dist-info/RECORD
